<?xml version="1.0" encoding="utf-8"?>
<TextureAtlas imagePath="ben_assets.png">
	<!-- Created with Adobe Animate version 21.0.7.42652 -->
	<!-- http://www.adobe.com/products/animate.html -->
	<SubTexture name="ben down0000" x="751" y="1257" width="350" height="381" frameX="0" frameY="-8" frameWidth="350" frameHeight="391"/>
	<SubTexture name="ben down0001" x="751" y="1257" width="350" height="381" frameX="0" frameY="-8" frameWidth="350" frameHeight="391"/>
	<SubTexture name="ben down0002" x="10" y="1638" width="337" height="391" frameX="-6" frameY="0" frameWidth="350" frameHeight="391"/>
	<SubTexture name="ben down0003" x="10" y="1638" width="337" height="391" frameX="-6" frameY="0" frameWidth="350" frameHeight="391"/>
	<SubTexture name="ben down0004" x="10" y="1638" width="337" height="391" frameX="-6" frameY="0" frameWidth="350" frameHeight="391"/>
	<SubTexture name="ben down0005" x="10" y="1638" width="337" height="391" frameX="-6" frameY="0" frameWidth="350" frameHeight="391"/>
	<SubTexture name="ben down0006" x="10" y="1638" width="337" height="391" frameX="-6" frameY="0" frameWidth="350" frameHeight="391"/>
	<SubTexture name="ben down0007" x="10" y="1638" width="337" height="391" frameX="-6" frameY="0" frameWidth="350" frameHeight="391"/>
	<SubTexture name="ben down0008" x="10" y="1638" width="337" height="391" frameX="-6" frameY="0" frameWidth="350" frameHeight="391"/>
	<SubTexture name="ben down0009" x="10" y="1638" width="337" height="391" frameX="-6" frameY="0" frameWidth="350" frameHeight="391"/>
	<SubTexture name="ben down0010" x="10" y="1638" width="337" height="391" frameX="-6" frameY="0" frameWidth="350" frameHeight="391"/>
	<SubTexture name="ben down0011" x="10" y="1638" width="337" height="391" frameX="-6" frameY="0" frameWidth="350" frameHeight="391"/>
	<SubTexture name="ben down0012" x="10" y="1638" width="337" height="391" frameX="-6" frameY="0" frameWidth="350" frameHeight="391"/>
	<SubTexture name="ben down0013" x="10" y="1638" width="337" height="391" frameX="-6" frameY="0" frameWidth="350" frameHeight="391"/>
	<SubTexture name="ben down0014" x="10" y="1638" width="337" height="391" frameX="-6" frameY="0" frameWidth="350" frameHeight="391"/>
	<SubTexture name="ben down0015" x="10" y="1638" width="337" height="391" frameX="-6" frameY="0" frameWidth="350" frameHeight="391"/>
	<SubTexture name="ben down0016" x="10" y="1638" width="337" height="391" frameX="-6" frameY="0" frameWidth="350" frameHeight="391"/>
	<SubTexture name="ben down0017" x="10" y="1638" width="337" height="391" frameX="-6" frameY="0" frameWidth="350" frameHeight="391"/>
	<SubTexture name="ben down0018" x="10" y="1638" width="337" height="391" frameX="-6" frameY="0" frameWidth="350" frameHeight="391"/>
	<SubTexture name="ben down0019" x="10" y="1638" width="337" height="391" frameX="-6" frameY="0" frameWidth="350" frameHeight="391"/>
	<SubTexture name="ben down0020" x="10" y="1638" width="337" height="391" frameX="-6" frameY="0" frameWidth="350" frameHeight="391"/>
	<SubTexture name="ben down0021" x="10" y="1638" width="337" height="391" frameX="-6" frameY="0" frameWidth="350" frameHeight="391"/>
	<SubTexture name="ben down0022" x="10" y="1638" width="337" height="391" frameX="-6" frameY="0" frameWidth="350" frameHeight="391"/>
	<SubTexture name="ben down0023" x="10" y="1638" width="337" height="391" frameX="-6" frameY="0" frameWidth="350" frameHeight="391"/>
	<SubTexture name="ben down0024" x="10" y="1638" width="337" height="391" frameX="-6" frameY="0" frameWidth="350" frameHeight="391"/>
	<SubTexture name="ben down0025" x="10" y="1638" width="337" height="391" frameX="-6" frameY="0" frameWidth="350" frameHeight="391"/>
	<SubTexture name="ben down0026" x="10" y="1638" width="337" height="391" frameX="-6" frameY="0" frameWidth="350" frameHeight="391"/>
	<SubTexture name="ben down0027" x="10" y="1638" width="337" height="391" frameX="-6" frameY="0" frameWidth="350" frameHeight="391"/>
	<SubTexture name="ben down0028" x="10" y="1638" width="337" height="391" frameX="-6" frameY="0" frameWidth="350" frameHeight="391"/>
	<SubTexture name="ben down0029" x="10" y="1638" width="337" height="391" frameX="-6" frameY="0" frameWidth="350" frameHeight="391"/>
	<SubTexture name="ben fall0000" x="10" y="10" width="507" height="387" frameX="0" frameY="0" frameWidth="559" frameHeight="808"/>
	<SubTexture name="ben fall0001" x="10" y="10" width="507" height="387" frameX="0" frameY="0" frameWidth="559" frameHeight="808"/>
	<SubTexture name="ben fall0002" x="10" y="413" width="510" height="375" frameX="-10" frameY="-84" frameWidth="559" frameHeight="808"/>
	<SubTexture name="ben fall0003" x="10" y="413" width="510" height="375" frameX="-10" frameY="-84" frameWidth="559" frameHeight="808"/>
	<SubTexture name="ben fall0004" x="533" y="10" width="514" height="365" frameX="-32" frameY="-186" frameWidth="559" frameHeight="808"/>
	<SubTexture name="ben fall0005" x="533" y="10" width="514" height="365" frameX="-32" frameY="-186" frameWidth="559" frameHeight="808"/>
	<SubTexture name="ben fall0006" x="10" y="804" width="469" height="379" frameX="-44" frameY="-345" frameWidth="559" frameHeight="808"/>
	<SubTexture name="ben fall0007" x="10" y="804" width="469" height="379" frameX="-44" frameY="-345" frameWidth="559" frameHeight="808"/>
	<SubTexture name="ben fall0008" x="495" y="805" width="544" height="315" frameX="-15" frameY="-483" frameWidth="559" frameHeight="808"/>
	<SubTexture name="ben fall0009" x="495" y="805" width="544" height="315" frameX="-15" frameY="-483" frameWidth="559" frameHeight="808"/>
	<SubTexture name="ben fall0010" x="1117" y="1257" width="337" height="385" frameX="-136" frameY="-423" frameWidth="559" frameHeight="808"/>
	<SubTexture name="ben fall0011" x="1117" y="1257" width="337" height="385" frameX="-136" frameY="-423" frameWidth="559" frameHeight="808"/>
	<SubTexture name="ben fall0012" x="1822" y="849" width="279" height="390" frameX="-174" frameY="-418" frameWidth="559" frameHeight="808"/>
	<SubTexture name="ben fall0013" x="1822" y="849" width="279" height="390" frameX="-174" frameY="-418" frameWidth="559" frameHeight="808"/>
	<SubTexture name="ben idle0000" x="1063" y="10" width="356" height="361" frameX="-21" frameY="-18" frameWidth="380" frameHeight="381"/>
	<SubTexture name="ben idle0001" x="1063" y="10" width="356" height="361" frameX="-21" frameY="-18" frameWidth="380" frameHeight="381"/>
	<SubTexture name="ben idle0002" x="733" y="1654" width="358" height="357" frameX="-22" frameY="-22" frameWidth="380" frameHeight="381"/>
	<SubTexture name="ben idle0003" x="733" y="1654" width="358" height="357" frameX="-22" frameY="-22" frameWidth="380" frameHeight="381"/>
	<SubTexture name="ben idle0004" x="1449" y="452" width="355" height="359" frameX="-21" frameY="-20" frameWidth="380" frameHeight="381"/>
	<SubTexture name="ben idle0005" x="1449" y="452" width="355" height="359" frameX="-21" frameY="-20" frameWidth="380" frameHeight="381"/>
	<SubTexture name="ben idle0006" x="363" y="1638" width="354" height="371" frameX="-16" frameY="-10" frameWidth="380" frameHeight="381"/>
	<SubTexture name="ben idle0007" x="363" y="1638" width="354" height="371" frameX="-16" frameY="-10" frameWidth="380" frameHeight="381"/>
	<SubTexture name="ben idle0008" x="10" y="2045" width="330" height="381" frameX="-6" frameY="0" frameWidth="380" frameHeight="381"/>
	<SubTexture name="ben idle0009" x="10" y="2045" width="330" height="381" frameX="-6" frameY="0" frameWidth="380" frameHeight="381"/>
	<SubTexture name="ben idle0010" x="1449" y="827" width="329" height="381" frameX="-3" frameY="0" frameWidth="380" frameHeight="381"/>
	<SubTexture name="ben idle0011" x="1449" y="827" width="329" height="381" frameX="-3" frameY="0" frameWidth="380" frameHeight="381"/>
	<SubTexture name="ben idle0012" x="1820" y="452" width="327" height="381" frameX="-3" frameY="0" frameWidth="380" frameHeight="381"/>
	<SubTexture name="ben idle0013" x="1820" y="452" width="327" height="381" frameX="-3" frameY="0" frameWidth="380" frameHeight="381"/>
	<SubTexture name="ben idle0014" x="1846" y="10" width="323" height="378" frameX="-2" frameY="-3" frameWidth="380" frameHeight="381"/>
	<SubTexture name="ben idle0015" x="1846" y="10" width="323" height="378" frameX="-2" frameY="-3" frameWidth="380" frameHeight="381"/>
	<SubTexture name="ben idle0016" x="1107" y="1658" width="316" height="365" frameX="0" frameY="-16" frameWidth="380" frameHeight="381"/>
	<SubTexture name="ben idle0017" x="1107" y="1658" width="316" height="365" frameX="0" frameY="-16" frameWidth="380" frameHeight="381"/>
	<SubTexture name="ben idle0018" x="1805" y="1612" width="311" height="362" frameX="0" frameY="-18" frameWidth="380" frameHeight="381"/>
	<SubTexture name="ben idle0019" x="1805" y="1612" width="311" height="362" frameX="0" frameY="-18" frameWidth="380" frameHeight="381"/>
	<SubTexture name="ben idle0020" x="723" y="2027" width="310" height="365" frameX="-1" frameY="-16" frameWidth="380" frameHeight="381"/>
	<SubTexture name="ben idle0021" x="723" y="2027" width="310" height="365" frameX="-1" frameY="-16" frameWidth="380" frameHeight="381"/>
	<SubTexture name="ben idle0022" x="1470" y="1612" width="319" height="370" frameX="-1" frameY="-11" frameWidth="380" frameHeight="381"/>
	<SubTexture name="ben idle0023" x="1470" y="1612" width="319" height="370" frameX="-1" frameY="-11" frameWidth="380" frameHeight="381"/>
	<SubTexture name="ben idle0024" x="1470" y="1224" width="336" height="372" frameX="-8" frameY="-9" frameWidth="380" frameHeight="381"/>
	<SubTexture name="ben idle0025" x="1470" y="1224" width="336" height="372" frameX="-8" frameY="-9" frameWidth="380" frameHeight="381"/>
	<SubTexture name="ben idle0026" x="363" y="2025" width="344" height="368" frameX="-19" frameY="-12" frameWidth="380" frameHeight="381"/>
	<SubTexture name="ben idle0027" x="363" y="2025" width="344" height="368" frameX="-19" frameY="-12" frameWidth="380" frameHeight="381"/>
	<SubTexture name="ben left0000" x="1055" y="798" width="378" height="443" frameX="0" frameY="0" frameWidth="392" frameHeight="443"/>
	<SubTexture name="ben left0001" x="1055" y="798" width="378" height="443" frameX="0" frameY="0" frameWidth="392" frameHeight="443"/>
	<SubTexture name="ben left0002" x="1446" y="10" width="384" height="426" frameX="-8" frameY="-16" frameWidth="392" frameHeight="443"/>
	<SubTexture name="ben left0003" x="1446" y="10" width="384" height="426" frameX="-8" frameY="-16" frameWidth="392" frameHeight="443"/>
	<SubTexture name="ben left0004" x="1446" y="10" width="384" height="426" frameX="-8" frameY="-16" frameWidth="392" frameHeight="443"/>
	<SubTexture name="ben left0005" x="1446" y="10" width="384" height="426" frameX="-8" frameY="-16" frameWidth="392" frameHeight="443"/>
	<SubTexture name="ben left0006" x="1446" y="10" width="384" height="426" frameX="-8" frameY="-16" frameWidth="392" frameHeight="443"/>
	<SubTexture name="ben left0007" x="1446" y="10" width="384" height="426" frameX="-8" frameY="-16" frameWidth="392" frameHeight="443"/>
	<SubTexture name="ben left0008" x="1446" y="10" width="384" height="426" frameX="-8" frameY="-16" frameWidth="392" frameHeight="443"/>
	<SubTexture name="ben left0009" x="1446" y="10" width="384" height="426" frameX="-8" frameY="-16" frameWidth="392" frameHeight="443"/>
	<SubTexture name="ben left0010" x="1446" y="10" width="384" height="426" frameX="-8" frameY="-16" frameWidth="392" frameHeight="443"/>
	<SubTexture name="ben left0011" x="1446" y="10" width="384" height="426" frameX="-8" frameY="-16" frameWidth="392" frameHeight="443"/>
	<SubTexture name="ben left0012" x="1446" y="10" width="384" height="426" frameX="-8" frameY="-16" frameWidth="392" frameHeight="443"/>
	<SubTexture name="ben left0013" x="1446" y="10" width="384" height="426" frameX="-8" frameY="-16" frameWidth="392" frameHeight="443"/>
	<SubTexture name="ben left0014" x="1446" y="10" width="384" height="426" frameX="-8" frameY="-16" frameWidth="392" frameHeight="443"/>
	<SubTexture name="ben left0015" x="1446" y="10" width="384" height="426" frameX="-8" frameY="-16" frameWidth="392" frameHeight="443"/>
	<SubTexture name="ben left0016" x="1446" y="10" width="384" height="426" frameX="-8" frameY="-16" frameWidth="392" frameHeight="443"/>
	<SubTexture name="ben left0017" x="1446" y="10" width="384" height="426" frameX="-8" frameY="-16" frameWidth="392" frameHeight="443"/>
	<SubTexture name="ben left0018" x="1446" y="10" width="384" height="426" frameX="-8" frameY="-16" frameWidth="392" frameHeight="443"/>
	<SubTexture name="ben left0019" x="1446" y="10" width="384" height="426" frameX="-8" frameY="-16" frameWidth="392" frameHeight="443"/>
	<SubTexture name="ben left0020" x="1446" y="10" width="384" height="426" frameX="-8" frameY="-16" frameWidth="392" frameHeight="443"/>
	<SubTexture name="ben left0021" x="1446" y="10" width="384" height="426" frameX="-8" frameY="-16" frameWidth="392" frameHeight="443"/>
	<SubTexture name="ben left0022" x="1446" y="10" width="384" height="426" frameX="-8" frameY="-16" frameWidth="392" frameHeight="443"/>
	<SubTexture name="ben left0023" x="1446" y="10" width="384" height="426" frameX="-8" frameY="-16" frameWidth="392" frameHeight="443"/>
	<SubTexture name="ben left0024" x="1446" y="10" width="384" height="426" frameX="-8" frameY="-16" frameWidth="392" frameHeight="443"/>
	<SubTexture name="ben left0025" x="1446" y="10" width="384" height="426" frameX="-8" frameY="-16" frameWidth="392" frameHeight="443"/>
	<SubTexture name="ben left0026" x="1446" y="10" width="384" height="426" frameX="-8" frameY="-16" frameWidth="392" frameHeight="443"/>
	<SubTexture name="ben left0027" x="1446" y="10" width="384" height="426" frameX="-8" frameY="-16" frameWidth="392" frameHeight="443"/>
	<SubTexture name="ben left0028" x="1446" y="10" width="384" height="426" frameX="-8" frameY="-16" frameWidth="392" frameHeight="443"/>
	<SubTexture name="ben left0029" x="1446" y="10" width="384" height="426" frameX="-8" frameY="-16" frameWidth="392" frameHeight="443"/>
	<SubTexture name="ben right0000" x="536" y="391" width="448" height="398" frameX="-8" frameY="0" frameWidth="456" frameHeight="398"/>
	<SubTexture name="ben right0001" x="536" y="391" width="448" height="398" frameX="-8" frameY="0" frameWidth="456" frameHeight="398"/>
	<SubTexture name="ben right0002" x="1000" y="391" width="430" height="391" frameX="0" frameY="-6" frameWidth="456" frameHeight="398"/>
	<SubTexture name="ben right0003" x="1000" y="391" width="430" height="391" frameX="0" frameY="-6" frameWidth="456" frameHeight="398"/>
	<SubTexture name="ben right0004" x="1000" y="391" width="430" height="391" frameX="0" frameY="-6" frameWidth="456" frameHeight="398"/>
	<SubTexture name="ben right0005" x="1000" y="391" width="430" height="391" frameX="0" frameY="-6" frameWidth="456" frameHeight="398"/>
	<SubTexture name="ben right0006" x="1000" y="391" width="430" height="391" frameX="0" frameY="-6" frameWidth="456" frameHeight="398"/>
	<SubTexture name="ben right0007" x="1000" y="391" width="430" height="391" frameX="0" frameY="-6" frameWidth="456" frameHeight="398"/>
	<SubTexture name="ben right0008" x="1000" y="391" width="430" height="391" frameX="0" frameY="-6" frameWidth="456" frameHeight="398"/>
	<SubTexture name="ben right0009" x="1000" y="391" width="430" height="391" frameX="0" frameY="-6" frameWidth="456" frameHeight="398"/>
	<SubTexture name="ben right0010" x="1000" y="391" width="430" height="391" frameX="0" frameY="-6" frameWidth="456" frameHeight="398"/>
	<SubTexture name="ben right0011" x="1000" y="391" width="430" height="391" frameX="0" frameY="-6" frameWidth="456" frameHeight="398"/>
	<SubTexture name="ben right0012" x="1000" y="391" width="430" height="391" frameX="0" frameY="-6" frameWidth="456" frameHeight="398"/>
	<SubTexture name="ben right0013" x="1000" y="391" width="430" height="391" frameX="0" frameY="-6" frameWidth="456" frameHeight="398"/>
	<SubTexture name="ben right0014" x="1000" y="391" width="430" height="391" frameX="0" frameY="-6" frameWidth="456" frameHeight="398"/>
	<SubTexture name="ben right0015" x="1000" y="391" width="430" height="391" frameX="0" frameY="-6" frameWidth="456" frameHeight="398"/>
	<SubTexture name="ben right0016" x="1000" y="391" width="430" height="391" frameX="0" frameY="-6" frameWidth="456" frameHeight="398"/>
	<SubTexture name="ben right0017" x="1000" y="391" width="430" height="391" frameX="0" frameY="-6" frameWidth="456" frameHeight="398"/>
	<SubTexture name="ben right0018" x="1000" y="391" width="430" height="391" frameX="0" frameY="-6" frameWidth="456" frameHeight="398"/>
	<SubTexture name="ben right0019" x="1000" y="391" width="430" height="391" frameX="0" frameY="-6" frameWidth="456" frameHeight="398"/>
	<SubTexture name="ben right0020" x="1000" y="391" width="430" height="391" frameX="0" frameY="-6" frameWidth="456" frameHeight="398"/>
	<SubTexture name="ben right0021" x="1000" y="391" width="430" height="391" frameX="0" frameY="-6" frameWidth="456" frameHeight="398"/>
	<SubTexture name="ben right0022" x="1000" y="391" width="430" height="391" frameX="0" frameY="-6" frameWidth="456" frameHeight="398"/>
	<SubTexture name="ben right0023" x="1000" y="391" width="430" height="391" frameX="0" frameY="-6" frameWidth="456" frameHeight="398"/>
	<SubTexture name="ben right0024" x="1000" y="391" width="430" height="391" frameX="0" frameY="-6" frameWidth="456" frameHeight="398"/>
	<SubTexture name="ben right0025" x="1000" y="391" width="430" height="391" frameX="0" frameY="-6" frameWidth="456" frameHeight="398"/>
	<SubTexture name="ben right0026" x="1000" y="391" width="430" height="391" frameX="0" frameY="-6" frameWidth="456" frameHeight="398"/>
	<SubTexture name="ben right0027" x="1000" y="391" width="430" height="391" frameX="0" frameY="-6" frameWidth="456" frameHeight="398"/>
	<SubTexture name="ben right0028" x="1000" y="391" width="430" height="391" frameX="0" frameY="-6" frameWidth="456" frameHeight="398"/>
	<SubTexture name="ben right0029" x="1000" y="391" width="430" height="391" frameX="0" frameY="-6" frameWidth="456" frameHeight="398"/>
	<SubTexture name="ben up0000" x="10" y="1199" width="350" height="423" frameX="-2" frameY="0" frameWidth="359" frameHeight="423"/>
	<SubTexture name="ben up0001" x="10" y="1199" width="350" height="423" frameX="-2" frameY="0" frameWidth="359" frameHeight="423"/>
	<SubTexture name="ben up0002" x="376" y="1199" width="359" height="407" frameX="0" frameY="-15" frameWidth="359" frameHeight="423"/>
	<SubTexture name="ben up0003" x="376" y="1199" width="359" height="407" frameX="0" frameY="-15" frameWidth="359" frameHeight="423"/>
	<SubTexture name="ben up0004" x="376" y="1199" width="359" height="407" frameX="0" frameY="-15" frameWidth="359" frameHeight="423"/>
	<SubTexture name="ben up0005" x="376" y="1199" width="359" height="407" frameX="0" frameY="-15" frameWidth="359" frameHeight="423"/>
	<SubTexture name="ben up0006" x="376" y="1199" width="359" height="407" frameX="0" frameY="-15" frameWidth="359" frameHeight="423"/>
	<SubTexture name="ben up0007" x="376" y="1199" width="359" height="407" frameX="0" frameY="-15" frameWidth="359" frameHeight="423"/>
	<SubTexture name="ben up0008" x="376" y="1199" width="359" height="407" frameX="0" frameY="-15" frameWidth="359" frameHeight="423"/>
	<SubTexture name="ben up0009" x="376" y="1199" width="359" height="407" frameX="0" frameY="-15" frameWidth="359" frameHeight="423"/>
	<SubTexture name="ben up0010" x="376" y="1199" width="359" height="407" frameX="0" frameY="-15" frameWidth="359" frameHeight="423"/>
	<SubTexture name="ben up0011" x="376" y="1199" width="359" height="407" frameX="0" frameY="-15" frameWidth="359" frameHeight="423"/>
	<SubTexture name="ben up0012" x="376" y="1199" width="359" height="407" frameX="0" frameY="-15" frameWidth="359" frameHeight="423"/>
	<SubTexture name="ben up0013" x="376" y="1199" width="359" height="407" frameX="0" frameY="-15" frameWidth="359" frameHeight="423"/>
	<SubTexture name="ben up0014" x="376" y="1199" width="359" height="407" frameX="0" frameY="-15" frameWidth="359" frameHeight="423"/>
	<SubTexture name="ben up0015" x="376" y="1199" width="359" height="407" frameX="0" frameY="-15" frameWidth="359" frameHeight="423"/>
	<SubTexture name="ben up0016" x="376" y="1199" width="359" height="407" frameX="0" frameY="-15" frameWidth="359" frameHeight="423"/>
	<SubTexture name="ben up0017" x="376" y="1199" width="359" height="407" frameX="0" frameY="-15" frameWidth="359" frameHeight="423"/>
	<SubTexture name="ben up0018" x="376" y="1199" width="359" height="407" frameX="0" frameY="-15" frameWidth="359" frameHeight="423"/>
	<SubTexture name="ben up0019" x="376" y="1199" width="359" height="407" frameX="0" frameY="-15" frameWidth="359" frameHeight="423"/>
	<SubTexture name="ben up0020" x="376" y="1199" width="359" height="407" frameX="0" frameY="-15" frameWidth="359" frameHeight="423"/>
	<SubTexture name="ben up0021" x="376" y="1199" width="359" height="407" frameX="0" frameY="-15" frameWidth="359" frameHeight="423"/>
	<SubTexture name="ben up0022" x="376" y="1199" width="359" height="407" frameX="0" frameY="-15" frameWidth="359" frameHeight="423"/>
	<SubTexture name="ben up0023" x="376" y="1199" width="359" height="407" frameX="0" frameY="-15" frameWidth="359" frameHeight="423"/>
	<SubTexture name="ben up0024" x="376" y="1199" width="359" height="407" frameX="0" frameY="-15" frameWidth="359" frameHeight="423"/>
	<SubTexture name="ben up0025" x="376" y="1199" width="359" height="407" frameX="0" frameY="-15" frameWidth="359" frameHeight="423"/>
	<SubTexture name="ben up0026" x="376" y="1199" width="359" height="407" frameX="0" frameY="-15" frameWidth="359" frameHeight="423"/>
	<SubTexture name="ben up0027" x="376" y="1199" width="359" height="407" frameX="0" frameY="-15" frameWidth="359" frameHeight="423"/>
	<SubTexture name="ben up0028" x="376" y="1199" width="359" height="407" frameX="0" frameY="-15" frameWidth="359" frameHeight="423"/>
	<SubTexture name="ben up0029" x="376" y="1199" width="359" height="407" frameX="0" frameY="-15" frameWidth="359" frameHeight="423"/>
</TextureAtlas>
